README
setup.py
scripts/makePlots
singlEpoClass/__init__.py
singlEpoClass/funcsForSimulatedData.py
singlEpoClass/makeMc.py
singlEpoClass/photoz.py
singlEpoClass/plots.py
singlEpoClass/randomForest.py
singlEpoClass/redshiftIterator.py
singlEpoClass/survivalFunc.py
singlEpoClass.egg-info/PKG-INFO
singlEpoClass.egg-info/SOURCES.txt
singlEpoClass.egg-info/dependency_links.txt
singlEpoClass.egg-info/not-zip-safe
singlEpoClass.egg-info/pbr.json
singlEpoClass.egg-info/top_level.txt