Metadata-Version: 1.0
Name: singlEpoClass
Version: 1.2
Summary: Single Epoch Transient Classifier
Home-page: http://github.com/sofiatti/SingleEpochPhotometricClassifier
Author: Caroline Sofiatti
Author-email: sofiatti@berkeley.edu
License: UNKNOWN
Platform: UNKNOWN
